<sheet>
  <description>
    <title>Freeway Of Love</title>
    <artist>Aretha Franklin</artist>
    <composer>Unknown Composer</composer>
    <tempo bpm="Unknown"/>
    <copyright>Unknown Lead Sheet Author</copyright>
    <style>Unknown Style</style>
  </description>
  <notation>
    <bar>
      <opening>
        <keysignature>G</keysignature>
        <timesignature>4/4</timesignature>
        <barline class="double" repeat="1"/>
      </opening>
      <annotation>Intro 1/drums &amp; bass</annotation>
      G7
      /
      /
      /
    </bar>
    <bar>
      /
      /
      /
      /
      <closing>
        <simile class="single"/>
      </closing>
    </bar>
    <bar>
      /
      /
      /
      /
      <closing>
        <simile class="single"/>
      </closing>
    </bar>
    <bar>
      /
      /
      /
      /
      <closing>
        <barline class="double" repeat="3"/>
        <simile class="single"/>
      </closing>
    </bar>
    <bar>
      <annotation>keyboard riff</annotation>
      Am/G
      /
      G
      /
    </bar>
    <bar>
      /
      Am/G
      Dm/G
      Am/G
    </bar>
    <bar>
      Am/G
      /
      G
      /
    </bar>
    <bar>
      /
      Am/G
      Dm/G
      Am/G
      <closing>
        <barline class="double"/>
      </closing>
    </bar>
    <bar>
      <opening>
        <rehearsalmark class="segno"/>
        <barline class="double" repeat="1"/>
      </opening>
      <annotation>verse</annotation>
      G7
      /
      /
      /
    </bar>
    <bar>
      /
      /
      /
      /
      <closing>
        <simile class="single"/>
      </closing>
    </bar>
    <bar>
      /
      /
      /
      /
      <closing>
        <simile class="single"/>
      </closing>
    </bar>
    <bar>
      /
      /
      /
      /
      <closing>
        <barline class="double" repeat="4"/>
        <simile class="single"/>
      </closing>
    </bar>
    <bar>
      <annotation>bridge</annotation>
      Am7
      /
      /
      /
    </bar>
    <bar>
      Am7
      /
      Bm7
      /
    </bar>
    <bar>
      Cmaj
      /
      /
      /
    </bar>
    <bar>
      <annotation>Breaks</annotation>
      D
      /
      /
      /
    </bar>
    <bar>
      D
      /
      /
      /
    </bar>
    <bar>
      D
      /
      /
      /
      <closing>
        <rehearsalmark class="coda"/>
      </closing>
    </bar>
    <bar>
      D7
      /
      /
      /
    </bar>
    <bar>
      <opening>
        <barline class="double" repeat="1"/>
      </opening>
      <annotation>Refrain</annotation>
      G7
      /
      /
      /
    </bar>
    <bar>
      /
      /
      /
      /
      <closing>
        <simile class="single"/>
      </closing>
    </bar>
    <bar>
      /
      /
      /
      /
      <closing>
        <simile class="single"/>
      </closing>
    </bar>
    <bar>
      /
      /
      /
      /
      <closing>
        <rehearsalmark class="coda_dsal"/>
        <barline class="double" repeat="4"/>
        <simile class="single"/>
      </closing>
    </bar>
    <bar>
      <opening>
        <rehearsalmark class="coda"/>
      </opening>
      E7
      /
      /
      /
      <closing>
        <barline class="double"/>
      </closing>
    </bar>
    <bar>
      <opening>
        <barline class="double" repeat="1"/>
      </opening>
      A7
      /
      /
      /
    </bar>
    <bar>
      /
      /
      /
      /
      <closing>
        <simile class="single"/>
      </closing>
    </bar>
    <bar>
      /
      /
      /
      /
      <closing>
        <simile class="single"/>
      </closing>
    </bar>
    <bar>
      /
      /
      /
      <annotation>rep. ad lib</annotation>
      /
      <closing>
        <barline class="double" repeat="1"/>
        <simile class="single"/>
      </closing>
    </bar>
  </notation>
</sheet>
