<sheet>  <description>    <title>Sweet Dreams</title>    <artist>Eurythmics</artist>    <composer>Unknown Composer</composer>    <tempo bpm="Unknown"/>    <copyright>Unknown Lead Sheet Author</copyright>    <style>Unknown Style</style>  </description>  <notation>    <bar>      <opening>        <keysignature>C-</keysignature>        <timesignature>4/4</timesignature>        <barline class="double"/>      </opening>      <annotation>Intro</annotation>      Cm      /      /      /    </bar>    <bar>      Ab      /      G4      /    </bar>    <bar>      /      /      /      /      <closing>        <simile class="double"/>      </closing>    </bar>    <bar>      /      /      /      /    </bar>    <bar>      <opening>        <barline class="double" repeat="1"/>      </opening>      <annotation>refrain</annotation>      Cm      /      /      /    </bar>    <bar>      Ab      /      G4      /    </bar>    <bar>      /      /      /      /      <closing>        <simile class="double"/>      </closing>    </bar>    <bar>      /      /      /      /      <closing>        <barline class="double" repeat="4"/>      </closing>    </bar>    <bar>      <opening>        <rehearsalmark class="segno"/>      </opening>      <annotation>bridge</annotation>      Ab      /      /      /    </bar>    <bar>      G4      /      G      /    </bar>    <bar>      Cm      /      /      /    </bar>    <bar>      Ab      /      /      /    </bar>    <bar>      Ab      /      /      /    </bar>    <bar>      G      /      /      /      <closing>        <rehearsalmark class="coda"/>      </closing>    </bar>    <bar>      <opening>        <barline class="double" repeat="1"/>      </opening>      <annotation>refrain</annotation>      Cm      /      /      /    </bar>    <bar>      Ab      /      G4      /      <closing>        <rehearsalmark class="coda_dsal"/>        <barline class="double" repeat="4"/>      </closing>    </bar>    <bar>      <opening>        <rehearsalmark class="coda"/>        <barline class="double" repeat="1"/>      </opening>      <annotation>Interlude</annotation>      Cm      /      /      /    </bar>    <bar>      F      /      /      /    </bar>    <bar>      /      /      /      /      <closing>        <simile class="double"/>      </closing>    </bar>    <bar>      /      /      /      /      <closing>        <barline class="double" repeat="1"/>      </closing>    </bar>    <bar>      <opening>        <barline class="double" repeat="1"/>      </opening>      <annotation>solo &amp; refrain</annotation>      Cm      /      /      /    </bar>    <bar>      Ab      /      G4      /    </bar>    <bar>      /      /      /      /      <closing>        <simile class="double"/>      </closing>    </bar>    <bar>      /      <annotation>D.S., then refrain ad lib</annotation>      /      /      /      <closing>        <barline class="double" repeat="1"/>      </closing>    </bar>  </notation></sheet>