<sheet>
  <description>
    <title>Valerie</title>
    <artist>Amy Winehouse</artist>
    <composer>Unknown Composer</composer>
    <tempo bpm="Unknown"/>
    <copyright>Unknown Lead Sheet Author</copyright>
    <style>Unknown Style</style>
  </description>
  <notation>
    <bar>
      <opening>
        <keysignature>Eb</keysignature>
        <timesignature>4/4</timesignature>
        <barline class="double"/>
      </opening>
      <annotation>intro</annotation>
      Eb
      /
      /
      /
    </bar>
    <bar>
      /
      /
      /
      /
      <closing>
        <simile class="single"/>
      </closing>
    </bar>
    <bar>
      /
      /
      /
      /
      <closing>
        <simile class="double"/>
      </closing>
    </bar>
    <bar>
      /
      /
      /
      /
    </bar>
    <bar>
      <opening>
        <barline class="double" repeat="1"/>
      </opening>
      <annotation>verse</annotation>
      Ebmaj
      /
      /
      /
    </bar>
    <bar>
      /
      /
      /
      /
      <closing>
        <simile class="single"/>
      </closing>
    </bar>
    <bar>
      Fm7
      /
      /
      /
    </bar>
    <bar>
      /
      /
      /
      /
      <closing>
        <barline class="double" repeat="1"/>
        <simile class="single"/>
      </closing>
    </bar>
    <bar>
      <opening>
        <rehearsalmark class="segno"/>
      </opening>
      <annotation>bridge</annotation>
      Ab
      /
      /
      /
    </bar>
    <bar>
      Gm
      /
      /
      /
    </bar>
    <bar>
      /
      /
      /
      /
      <closing>
        <simile class="double"/>
      </closing>
    </bar>
    <bar>
      /
      /
      /
      /
    </bar>
    <bar>
      /
      /
      /
      /
      <closing>
        <simile class="double"/>
      </closing>
    </bar>
    <bar>
      /
      /
      /
      /
    </bar>
    <bar>
      Bb7
      /
      /
      /
    </bar>
    <bar>
      /
      /
      /
      /
      <closing>
        <barline class="double"/>
        <simile class="single"/>
      </closing>
    </bar>
    <bar>
      <opening>
        <barline class="double" repeat="1"/>
      </opening>
      <annotation>refrain</annotation>
      Ebmaj
      /
      /
      /
    </bar>
    <bar>
      /
      /
      /
      /
      <closing>
        <simile class="single"/>
      </closing>
    </bar>
    <bar>
      Fm7
      /
      /
      /
    </bar>
    <bar>
      /
      /
      /
      /
      <closing>
        <barline class="double" repeat="1"/>
        <simile class="single"/>
      </closing>
    </bar>
    <bar>
      <opening>
        <barline class="double" repeat="1"/>
      </opening>
      <annotation>verse 2</annotation>
      Ebmaj
      /
      /
      /
    </bar>
    <bar>
      /
      /
      /
      /
      <closing>
        <simile class="single"/>
      </closing>
    </bar>
    <bar>
      Fm7
      /
      /
      /
    </bar>
    <bar>
      /
      /
      /
      <annotation>D.S.</annotation>
      /
      <closing>
        <barline class="double" repeat="4"/>
        <simile class="single"/>
      </closing>
    </bar>
  </notation>
</sheet>
