<sheet>
  <description>
    <title>You're The One That I Want</title>
    <artist>John Farrar</artist>
    <composer>Unknown Composer</composer>
    <tempo bpm="Unknown"/>
    <copyright>Unknown Lead Sheet Author</copyright>
    <style>Unknown Style</style>
  </description>
  <notation>
    <bar>
      <opening>
        <keysignature>Ab</keysignature>
        <timesignature>4/4</timesignature>
        <barline class="double" repeat="1"/>
      </opening>
      <annotation>Intro</annotation>
      Gm
      /
      /
      /
    </bar>
    <bar>
      /
      /
      /
      /
      <closing>
        <barline class="double" repeat="1"/>
        <simile class="single"/>
      </closing>
    </bar>
    <bar>
      <opening>
        <barline class="double" repeat="1"/>
      </opening>
      <annotation>verse</annotation>
      Gm
      /
      /
      /
    </bar>
    <bar>
      /
      /
      /
      /
      <closing>
        <barline class="double" repeat="1"/>
        <simile class="single"/>
      </closing>
    </bar>
    <bar>
      Eb
      /
      /
      /
    </bar>
    <bar>
      Bb
      /
      /
      /
    </bar>
    <bar>
      D
      /
      /
      /
    </bar>
    <bar>
      Gm
      /
      /
      /
    </bar>
    <bar>
      Gm
      /
      /
      /
    </bar>
    <bar>
      /
      /
      /
      /
      <closing>
        <barline class="double"/>
        <simile class="single"/>
      </closing>
    </bar>
    <bar>
      <annotation>verse 2</annotation>
      Bb
      /
      /
      /
    </bar>
    <bar>
      Dm
      /
      /
      /
    </bar>
    <bar>
      Gm
      /
      /
      /
    </bar>
    <bar>
      Eb
      /
      /
      /
    </bar>
    <bar>
      Bb
      /
      /
      /
    </bar>
    <bar>
      Dm
      /
      /
      /
    </bar>
    <bar>
      Gm
      /
      /
      /
    </bar>
    <bar>
      Eb
      /
      /
      /
    </bar>
    <bar>
      /
      /
      /
      /
      <closing>
        <barline class="double"/>
        <simile class="single"/>
      </closing>
    </bar>
    <bar>
      <annotation>refrain</annotation>
      Ab
      /
      /
      /
    </bar>
    <bar>
      Ab
      /
      Db
      /
    </bar>
    <bar>
      Ab
      /
      /
      /
    </bar>
    <bar>
      Ab
      /
      Db
      /
    </bar>
    <bar>
      Ab
      /
      /
      /
    </bar>
    <bar>
      Ab
      /
      Db
      /
    </bar>
    <bar>
      Eb7
      /
      /
      /
    </bar>
    <bar>
      /
      /
      /
      <annotation>D.C./rep.refr. ad lib</annotation>
      /
      <closing>
        <barline class="double"/>
        <simile class="single"/>
      </closing>
    </bar>
  </notation>
</sheet>
